qsample/__init__.py
qsample/_modidx.py
qsample/callbacks.py
qsample/circuit.py
qsample/examples.py
qsample/math.py
qsample/noise.py
qsample/protocol.py
qsample/utils.py
qsample/sampler/__init__.py
qsample/sampler/direct.py
qsample/sampler/experimental.py
qsample/sampler/subset.py
qsample/sampler/tree.py
qsample/sim/__init__.py
qsample/sim/mixin.py
qsample/sim/stabilizer.py
qsample/sim/statevector.py
qsample-0.0.2.dist-info/LICENSE
qsample-0.0.2.dist-info/METADATA
qsample-0.0.2.dist-info/WHEEL
qsample-0.0.2.dist-info/entry_points.txt
qsample-0.0.2.dist-info/top_level.txt
qsample-0.0.2.dist-info/RECORD
