Metadata-Version: 2.1
Name: qsample
Version: 0.0.2
Summary: Efficient sampling of noisy quantum circuits and protocols
Home-page: https://github.com/dpwinter/qsample/tree/master/
Author: Don Winter
Author-email: don@wintr.de
License: Apache Software License 2.0
Keywords: qecc,circuit,protocol,sample,sampling
Platform: UNKNOWN
Classifier: Development Status :: 3 - Alpha
Classifier: Intended Audience :: Developers
Classifier: Natural Language :: English
Classifier: Programming Language :: Python :: 3.9
Classifier: Programming Language :: Python :: 3.10
Classifier: License :: OSI Approved :: Apache Software License
Requires-Python: >=3.9
License-File: LICENSE
Requires-Dist: anytree
Requires-Dist: chp-sim
Requires-Dist: dill
Requires-Dist: latextools
Requires-Dist: matplotlib
Requires-Dist: networkx
Requires-Dist: numpy
Requires-Dist: projectq
Requires-Dist: pydot
Requires-Dist: scipy
Requires-Dist: simpleeval
Requires-Dist: tqdm
Provides-Extra: dev
